cdsl.cp38-win_amd64.pyd
cdsl/__init__.py
cdsl-0.1.dev0.dist-info/LICENSE
cdsl-0.1.dev0.dist-info/METADATA
cdsl-0.1.dev0.dist-info/WHEEL
cdsl-0.1.dev0.dist-info/top_level.txt
cdsl-0.1.dev0.dist-info/RECORD
